nodejobs/__init__.py
nodejobs/jobdb.py
nodejobs/jobs.py
nodejobs/jobs_raw_test.py
nodejobs/jobs_verbose_test.py
nodejobs/processes.py
nodejobs/run_job.py
nodejobs/run_job_test.py
nodejobs/dependencies/BaseData.py
nodejobs/dependencies/BaseService.py
nodejobs/dependencies/__init__.py
nodejobs/dependencies/nosqlite.py
nodejobs-0.3.0.dist-info/licenses/LICENSE.md
nodejobs-0.3.0.dist-info/METADATA
nodejobs-0.3.0.dist-info/WHEEL
nodejobs-0.3.0.dist-info/top_level.txt
nodejobs-0.3.0.dist-info/RECORD
