Metadata-Version: 2.4
Name: nodejobs
Version: 0.3.0
Summary: A simple job‐management library with Processes, JobDB, and Jobs classes
Author-email: Justin Girard <justingirard@decelium.com>
License: MIT
Project-URL: Homepage, https://github.com/Decelium/nodejobs
Classifier: Development Status :: 2 - Pre-Alpha
Classifier: Intended Audience :: Developers
Classifier: Topic :: System :: Monitoring
Classifier: License :: OSI Approved :: MIT License
Classifier: Programming Language :: Python :: 3
Requires-Python: >=3.0
License-File: LICENSE.md
Requires-Dist: psutil
Dynamic: license-file
